{
  "id": "joseph-dream",
  "kind": "plot-order",
  "character": "joseph",
  "title": "꿈과 채색옷",
  "icon": "🌈",
  "requires": ["jacob-reunion"],
  "intro": "요셉이 왜 형들에게 미움을 받았을까요?",
  "scenes": [
    {
      "title": "아버지가 요셉을 특별히 사랑했어요",
      "quote": "야곱이 요셉에게 채색옷을 지어 입혔어요",
      "ref": "창세기 37:3",
      "emoji": "🧥"
    },
    {
      "title": "형들이 시기했어요",
      "quote": "형들이 아버지가 요셉을 더 사랑하는 것을 알고 미워했어요",
      "ref": "창세기 37:4",
      "emoji": "😠"
    },
    {
      "title": "곡식 단 꿈을 꾸었어요",
      "quote": "내 곡식 단이 일어서고 형들의 단이 절하는 꿈을 꾸었어요",
      "ref": "창세기 37:7",
      "emoji": "🌾"
    },
    {
      "title": "해와 달과 별의 꿈도 꾸었어요",
      "quote": "해와 달과 열한 별이 내게 절하였어요",
      "ref": "창세기 37:9",
      "emoji": "⭐"
    }
  ],
  "epilogue": "하나님이 요셉에게 미래를 꿈으로 보여주셨어요. 하지만 형들은 이 꿈 때문에 더 질투했지요. 하나님이 주신 꿈은 당장 이해받지 못해도 때가 되면 이루어져요. 다음엔 요셉이 어떤 고난을 겪게 되는지 볼까요?",
  "next": "joseph-sold"
}
